odoo8_addon_l10n_es_payment_order_confirming_bankia-8.0.1.0.0.99.dev4-py3.6-nspkg.pth
odoo_addons/l10n_es_payment_order_confirming_bankia/README.rst
odoo_addons/l10n_es_payment_order_confirming_bankia/__init__.py
odoo_addons/l10n_es_payment_order_confirming_bankia/__openerp__.py
odoo_addons/l10n_es_payment_order_confirming_bankia/data/payment_type_data.xml
odoo_addons/l10n_es_payment_order_confirming_bankia/i18n/ca.po
odoo_addons/l10n_es_payment_order_confirming_bankia/i18n/es.po
odoo_addons/l10n_es_payment_order_confirming_bankia/i18n/l10n_es_payment_order_confirming_bankia.pot
odoo_addons/l10n_es_payment_order_confirming_bankia/models/__init__.py
odoo_addons/l10n_es_payment_order_confirming_bankia/models/payment_mode.py
odoo_addons/l10n_es_payment_order_confirming_bankia/static/description/icon.png
odoo_addons/l10n_es_payment_order_confirming_bankia/views/payment_mode_view.xml
odoo_addons/l10n_es_payment_order_confirming_bankia/wizard/__init__.py
odoo_addons/l10n_es_payment_order_confirming_bankia/wizard/confirming_bankia.py
odoo_addons/l10n_es_payment_order_confirming_bankia/wizard/export_csb.py
odoo8_addon_l10n_es_payment_order_confirming_bankia-8.0.1.0.0.99.dev4.dist-info/METADATA
odoo8_addon_l10n_es_payment_order_confirming_bankia-8.0.1.0.0.99.dev4.dist-info/WHEEL
odoo8_addon_l10n_es_payment_order_confirming_bankia-8.0.1.0.0.99.dev4.dist-info/namespace_packages.txt
odoo8_addon_l10n_es_payment_order_confirming_bankia-8.0.1.0.0.99.dev4.dist-info/top_level.txt
odoo8_addon_l10n_es_payment_order_confirming_bankia-8.0.1.0.0.99.dev4.dist-info/RECORD
