Metadata-Version: 2.1
Name: odoo8-addon-l10n-es-payment-order-confirming-bankia
Version: 8.0.1.0.0.99.dev4
Summary: Exportación de fichero bancario Confirming para Bankia
Home-page: https://github.com/OCA/l10n-spain
Author: Soluntec, Odoo Community Association (OCA)
Author-email: support@odoo-community.org
License: AGPL-3
Platform: UNKNOWN
Classifier: Programming Language :: Python
Classifier: Framework :: Odoo
Classifier: License :: OSI Approved :: GNU Affero General Public License v3
Requires-Python: ~=2.7
Requires-Dist: odoo8-addon-l10n-es-payment-order
Requires-Dist: odoo (<9.0a,>=8.0a)
